README.md
setup.py
anutshell/__init__.py
anutshell/evaluator.py
anutshell/utils.py
anutshell/dataset/__init__.py
anutshell/dataset/anutshell_dataset.py
anutshell/dataset/anutshell_field.py
anutshell/dataset/anutshell_iterator.py
anutshell/model/Decoder.py
anutshell/model/Encoder.py
anutshell/model/__init__.py
anutshell/model/anutshell_model.py
brief.egg-info/PKG-INFO
brief.egg-info/SOURCES.txt
brief.egg-info/dependency_links.txt
brief.egg-info/entry_points.txt
brief.egg-info/requires.txt
brief.egg-info/top_level.txt